rfc123/__init__.py
rfc123/download_file.py
rfc123-0.1.dist-info/LICENSE
rfc123-0.1.dist-info/METADATA
rfc123-0.1.dist-info/WHEEL
rfc123-0.1.dist-info/entry_points.txt
rfc123-0.1.dist-info/top_level.txt
rfc123-0.1.dist-info/RECORD
