Metadata-Version: 2.1
Name: rfc123
Version: 0.1
Summary: Download RFC.Java from GitHub
Author: Rajesh
License: MIT
Requires-Python: >=3.6
License-File: LICENSE
